vezor_sdk/__init__.py
vezor_sdk/cliente.py
vezor_sdk/evoapi.py
vezor_sdk/kommo.py
vezor_sdk-0.1.2.dist-info/licenses/LICENSE
vezor_sdk-0.1.2.dist-info/METADATA
vezor_sdk-0.1.2.dist-info/WHEEL
vezor_sdk-0.1.2.dist-info/top_level.txt
vezor_sdk-0.1.2.dist-info/RECORD
