Metadata-Version: 2.4
Name: vezor_sdk
Version: 0.1.2
Summary: Bridge Python SDK da Vezor
Home-page: https://github.com/vezor-group/vezor_sdk
Author: Breno Leone
Author-email: Breno Leone <admin.platform@vezor.com.br>
License-Expression: MIT
Classifier: Programming Language :: Python :: 3
Classifier: Programming Language :: Python :: 3.8
Classifier: Programming Language :: Python :: 3.9
Classifier: Programming Language :: Python :: 3.10
Classifier: Operating System :: OS Independent
Requires-Python: >=3.8
License-File: LICENSE
Requires-Dist: requests>=2.31.0
Dynamic: author
Dynamic: home-page
Dynamic: license-file
Dynamic: requires-python
